odoo10_addon_product_custom_info-10.0.1.0.0.99.dev2-py2.7-nspkg.pth
odoo/addons/product_custom_info/README.rst
odoo/addons/product_custom_info/__init__.py
odoo/addons/product_custom_info/__manifest__.py
odoo/addons/product_custom_info/i18n/es.po
odoo/addons/product_custom_info/i18n/product_custom_info.pot
odoo/addons/product_custom_info/models/__init__.py
odoo/addons/product_custom_info/models/product_product.py
odoo/addons/product_custom_info/models/product_template.py
odoo/addons/product_custom_info/static/description/icon.png
odoo/addons/product_custom_info/views/product_product_view.xml
odoo/addons/product_custom_info/views/product_template_view.xml
odoo10_addon_product_custom_info-10.0.1.0.0.99.dev2.dist-info/METADATA
odoo10_addon_product_custom_info-10.0.1.0.0.99.dev2.dist-info/RECORD
odoo10_addon_product_custom_info-10.0.1.0.0.99.dev2.dist-info/WHEEL
odoo10_addon_product_custom_info-10.0.1.0.0.99.dev2.dist-info/namespace_packages.txt
odoo10_addon_product_custom_info-10.0.1.0.0.99.dev2.dist-info/top_level.txt
